[
    null,
    {
        "id": 1,
        "animationId": 41,
        "consumable": true,
        "damage": {
            "critical": false,
            "elementId": 0,
            "formula": "0",
            "type": 0,
            "variance": 20
        },
        "description": "HPを少量回復する。\n※上限：10個",
        "effects": [
            {
                "code": 11,
                "dataId": 0,
                "value1": 0.3,
                "value2": 0
            }
        ],
        "hitType": 0,
        "iconIndex": 0,
        "itypeId": 1,
        "name": "回復薬",
        "note": "itemMaxNum:10",
        "occasion": 0,
        "price": 50,
        "repeats": 1,
        "scope": 7,
        "speed": 0,
        "successRate": 100,
        "tpGain": 0
    },
    {
        "id": 2,
        "animationId": 41,
        "consumable": true,
        "damage": {
            "critical": false,
            "elementId": 0,
            "formula": "0",
            "type": 0,
            "variance": 20
        },
        "description": "SPを少量回復する。\n※上限：10個",
        "effects": [
            {
                "code": 12,
                "dataId": 0,
                "value1": 0.2,
                "value2": 0
            }
        ],
        "hitType": 0,
        "iconIndex": 0,
        "itypeId": 1,
        "name": "栄養剤",
        "note": "itemMaxNum:10",
        "occasion": 0,
        "price": 50,
        "repeats": 1,
        "scope": 7,
        "speed": 0,
        "successRate": 100,
        "tpGain": 0
    },
    {
        "id": 3,
        "animationId": 45,
        "consumable": true,
        "damage": {
            "critical": false,
            "elementId": 0,
            "formula": "0",
            "type": 0,
            "variance": 20
        },
        "description": "出血状態を治療し、HPを極小回復。\n※上限：10個",
        "effects": [
            {
                "code": 22,
                "dataId": 4,
                "value1": 1,
                "value2": 0
            },
            {
                "code": 22,
                "dataId": 5,
                "value1": 1,
                "value2": 0
            },
            {
                "code": 22,
                "dataId": 6,
                "value1": 1,
                "value2": 0
            },
            {
                "code": 11,
                "dataId": 0,
                "value1": 0.15,
                "value2": 0
            }
        ],
        "hitType": 0,
        "iconIndex": 0,
        "itypeId": 1,
        "name": "止血剤",
        "note": "itemMaxNum:10\n",
        "occasion": 0,
        "price": 40,
        "repeats": 1,
        "scope": 11,
        "speed": 0,
        "successRate": 100,
        "tpGain": 0
    },
    {
        "id": 4,
        "animationId": 49,
        "consumable": true,
        "damage": {
            "critical": false,
            "elementId": 0,
            "formula": "b.mhp / 2",
            "type": 3,
            "variance": 20
        },
        "description": "",
        "effects": [
            {
                "code": 22,
                "dataId": 1,
                "value1": 1,
                "value2": 0
            }
        ],
        "hitType": 0,
        "iconIndex": 0,
        "itypeId": 1,
        "name": "活力剤",
        "note": "",
        "occasion": 0,
        "price": 300,
        "repeats": 1,
        "scope": 9,
        "speed": 0,
        "successRate": 100,
        "tpGain": 0
    },
    {
        "id": 5,
        "animationId": 0,
        "consumable": true,
        "damage": {
            "critical": false,
            "elementId": 0,
            "formula": "0",
            "type": 0,
            "variance": 20
        },
        "description": "",
        "effects": [],
        "hitType": 0,
        "iconIndex": 0,
        "itypeId": 1,
        "name": "鍵",
        "note": "",
        "occasion": 3,
        "price": 0,
        "repeats": 1,
        "scope": 0,
        "speed": 0,
        "successRate": 100,
        "tpGain": 0
    },
    {
        "id": 6,
        "animationId": 41,
        "consumable": true,
        "damage": {
            "critical": false,
            "elementId": 0,
            "formula": "0",
            "type": 0,
            "variance": 20
        },
        "description": "HP/SPを少量回復する。\n※上限：10個",
        "effects": [
            {
                "code": 11,
                "dataId": 0,
                "value1": 0.2,
                "value2": 0
            },
            {
                "code": 12,
                "dataId": 0,
                "value1": 0.2,
                "value2": 0
            }
        ],
        "hitType": 0,
        "iconIndex": 0,
        "itypeId": 1,
        "name": "複合薬",
        "note": "itemMaxNum:10",
        "occasion": 0,
        "price": 70,
        "repeats": 1,
        "scope": 7,
        "speed": 0,
        "successRate": 100,
        "tpGain": 0
    },
    {
        "id": 7,
        "animationId": 41,
        "consumable": true,
        "damage": {
            "critical": false,
            "elementId": 0,
            "formula": "0",
            "type": 0,
            "variance": 20
        },
        "description": "HPを中量回復する。\n※上限：10個",
        "effects": [
            {
                "code": 11,
                "dataId": 0,
                "value1": 0.4,
                "value2": 0
            }
        ],
        "hitType": 0,
        "iconIndex": 0,
        "itypeId": 1,
        "name": "高回復薬",
        "note": "itemMaxNum:10",
        "occasion": 0,
        "price": 120,
        "repeats": 1,
        "scope": 7,
        "speed": 0,
        "successRate": 100,
        "tpGain": 0
    },
    {
        "id": 8,
        "animationId": 41,
        "consumable": true,
        "damage": {
            "critical": false,
            "elementId": 0,
            "formula": "0",
            "type": 0,
            "variance": 20
        },
        "description": "SPを中量回復する。\n※上限：10個",
        "effects": [
            {
                "code": 12,
                "dataId": 0,
                "value1": 0.4,
                "value2": 0
            }
        ],
        "hitType": 0,
        "iconIndex": 0,
        "itypeId": 1,
        "name": "高栄養剤",
        "note": "itemMaxNum:10",
        "occasion": 0,
        "price": 120,
        "repeats": 1,
        "scope": 7,
        "speed": 0,
        "successRate": 100,
        "tpGain": 0
    },
    {
        "id": 9,
        "animationId": 45,
        "consumable": true,
        "damage": {
            "critical": false,
            "elementId": 0,
            "formula": "0",
            "type": 0,
            "variance": 20
        },
        "description": "",
        "effects": [
            {
                "code": 22,
                "dataId": 4,
                "value1": 1,
                "value2": 0
            },
            {
                "code": 22,
                "dataId": 5,
                "value1": 1,
                "value2": 0
            },
            {
                "code": 22,
                "dataId": 6,
                "value1": 1,
                "value2": 0
            },
            {
                "code": 22,
                "dataId": 8,
                "value1": 1,
                "value2": 0
            },
            {
                "code": 22,
                "dataId": 9,
                "value1": 1,
                "value2": 0
            },
            {
                "code": 22,
                "dataId": 10,
                "value1": 1,
                "value2": 0
            }
        ],
        "hitType": 0,
        "iconIndex": 0,
        "itypeId": 1,
        "name": "高止血剤",
        "note": "itemMaxNum:10",
        "occasion": 0,
        "price": 200,
        "repeats": 1,
        "scope": 7,
        "speed": 0,
        "successRate": 100,
        "tpGain": 0
    },
    {
        "id": 10,
        "animationId": 41,
        "consumable": true,
        "damage": {
            "critical": false,
            "elementId": 0,
            "formula": "0",
            "type": 0,
            "variance": 20
        },
        "description": "HP/SPを中量回復する。\n※上限：10個",
        "effects": [
            {
                "code": 11,
                "dataId": 0,
                "value1": 0.35,
                "value2": 0
            },
            {
                "code": 12,
                "dataId": 0,
                "value1": 0.35,
                "value2": 0
            }
        ],
        "hitType": 0,
        "iconIndex": 0,
        "itypeId": 1,
        "name": "高複合薬",
        "note": "itemMaxNum:10",
        "occasion": 0,
        "price": 200,
        "repeats": 1,
        "scope": 7,
        "speed": 0,
        "successRate": 100,
        "tpGain": 0
    },
    {
        "id": 11,
        "animationId": 41,
        "consumable": true,
        "damage": {
            "critical": false,
            "elementId": 0,
            "formula": "0",
            "type": 0,
            "variance": 20
        },
        "description": "HPを大量回復する。\n※上限：5個",
        "effects": [
            {
                "code": 11,
                "dataId": 0,
                "value1": 0.8,
                "value2": 0
            }
        ],
        "hitType": 0,
        "iconIndex": 0,
        "itypeId": 1,
        "name": "極回復薬",
        "note": "itemMaxNum:5",
        "occasion": 0,
        "price": 300,
        "repeats": 1,
        "scope": 7,
        "speed": 0,
        "successRate": 100,
        "tpGain": 0
    },
    {
        "id": 12,
        "animationId": 41,
        "consumable": true,
        "damage": {
            "critical": false,
            "elementId": 0,
            "formula": "0",
            "type": 0,
            "variance": 20
        },
        "description": "SPを大量回復する。\n※上限：5個",
        "effects": [
            {
                "code": 12,
                "dataId": 0,
                "value1": 0.8,
                "value2": 0
            }
        ],
        "hitType": 0,
        "iconIndex": 0,
        "itypeId": 1,
        "name": "極栄養剤",
        "note": "itemMaxNum:5",
        "occasion": 0,
        "price": 300,
        "repeats": 1,
        "scope": 7,
        "speed": 0,
        "successRate": 100,
        "tpGain": 0
    },
    {
        "id": 13,
        "animationId": 41,
        "consumable": true,
        "damage": {
            "critical": false,
            "elementId": 0,
            "formula": "0",
            "type": 0,
            "variance": 20
        },
        "description": "HP/SPを大量回復する。\n※上限：5個",
        "effects": [
            {
                "code": 11,
                "dataId": 0,
                "value1": 0.5,
                "value2": 0
            },
            {
                "code": 12,
                "dataId": 0,
                "value1": 0.5,
                "value2": 0
            }
        ],
        "hitType": 0,
        "iconIndex": 0,
        "itypeId": 1,
        "name": "極複合薬",
        "note": "itemMaxNum:5",
        "occasion": 0,
        "price": 400,
        "repeats": 1,
        "scope": 7,
        "speed": 0,
        "successRate": 100,
        "tpGain": 0
    },
    {
        "id": 14,
        "animationId": 0,
        "consumable": true,
        "damage": {
            "critical": false,
            "elementId": 0,
            "formula": "0",
            "type": 0,
            "variance": 20
        },
        "description": "",
        "effects": [],
        "hitType": 0,
        "iconIndex": 0,
        "itypeId": 1,
        "name": "",
        "note": "",
        "occasion": 0,
        "price": 0,
        "repeats": 1,
        "scope": 7,
        "speed": 0,
        "successRate": 100,
        "tpGain": 0
    },
    {
        "id": 15,
        "animationId": 0,
        "consumable": true,
        "damage": {
            "critical": false,
            "elementId": 0,
            "formula": "0",
            "type": 0,
            "variance": 20
        },
        "description": "",
        "effects": [
            {
                "code": 31,
                "dataId": 0,
                "value1": 5,
                "value2": 0
            }
        ],
        "hitType": 0,
        "iconIndex": 0,
        "itypeId": 1,
        "name": "体力強化剤",
        "note": "",
        "occasion": 1,
        "price": 0,
        "repeats": 1,
        "scope": 7,
        "speed": 0,
        "successRate": 100,
        "tpGain": 0
    },
    {
        "id": 16,
        "animationId": 0,
        "consumable": true,
        "damage": {
            "critical": false,
            "elementId": 0,
            "formula": "0",
            "type": 0,
            "variance": 20
        },
        "description": "",
        "effects": [],
        "hitType": 0,
        "iconIndex": 0,
        "itypeId": 1,
        "name": "",
        "note": "",
        "occasion": 0,
        "price": 0,
        "repeats": 1,
        "scope": 7,
        "speed": 0,
        "successRate": 100,
        "tpGain": 0
    },
    {
        "id": 17,
        "animationId": 0,
        "consumable": true,
        "damage": {
            "critical": false,
            "elementId": 0,
            "formula": "0",
            "type": 0,
            "variance": 20
        },
        "description": "",
        "effects": [
            {
                "code": 41,
                "dataId": 0,
                "value1": 1,
                "value2": 0
            }
        ],
        "hitType": 0,
        "iconIndex": 0,
        "itypeId": 1,
        "name": "煙幕",
        "note": "",
        "occasion": 1,
        "price": 0,
        "repeats": 1,
        "scope": 7,
        "speed": 0,
        "successRate": 100,
        "tpGain": 0
    },
    {
        "id": 18,
        "animationId": 0,
        "consumable": true,
        "damage": {
            "critical": false,
            "elementId": 0,
            "formula": "0",
            "type": 0,
            "variance": 20
        },
        "description": "",
        "effects": [],
        "hitType": 0,
        "iconIndex": 0,
        "itypeId": 1,
        "name": "",
        "note": "",
        "occasion": 2,
        "price": 0,
        "repeats": 1,
        "scope": 7,
        "speed": 0,
        "successRate": 100,
        "tpGain": 0
    },
    {
        "id": 19,
        "animationId": 0,
        "consumable": true,
        "damage": {
            "critical": false,
            "elementId": 0,
            "formula": "0",
            "type": 0,
            "variance": 20
        },
        "description": "使用する事で最大HPが1上昇する丸薬。",
        "effects": [
            {
                "code": 42,
                "dataId": 0,
                "value1": 1,
                "value2": 0
            }
        ],
        "hitType": 0,
        "iconIndex": 0,
        "itypeId": 1,
        "name": "成長剤HP",
        "note": "",
        "occasion": 2,
        "price": 50,
        "repeats": 1,
        "scope": 11,
        "speed": 0,
        "successRate": 100,
        "tpGain": 0
    },
    {
        "id": 20,
        "animationId": 0,
        "consumable": true,
        "damage": {
            "critical": false,
            "elementId": 0,
            "formula": "0",
            "type": 0,
            "variance": 20
        },
        "description": "使用する事で最大SPが1上昇する丸薬。",
        "effects": [
            {
                "code": 42,
                "dataId": 1,
                "value1": 1,
                "value2": 0
            }
        ],
        "hitType": 0,
        "iconIndex": 0,
        "itypeId": 1,
        "name": "成長剤SP",
        "note": "",
        "occasion": 2,
        "price": 50,
        "repeats": 1,
        "scope": 11,
        "speed": 0,
        "successRate": 100,
        "tpGain": 0
    },
    {
        "id": 21,
        "animationId": 0,
        "consumable": true,
        "damage": {
            "critical": false,
            "elementId": 0,
            "formula": "0",
            "type": 0,
            "variance": 20
        },
        "description": "使用する事で攻撃力が1上昇する丸薬。",
        "effects": [
            {
                "code": 42,
                "dataId": 2,
                "value1": 1,
                "value2": 0
            }
        ],
        "hitType": 0,
        "iconIndex": 0,
        "itypeId": 1,
        "name": "成長剤ATK",
        "note": "",
        "occasion": 2,
        "price": 50,
        "repeats": 1,
        "scope": 11,
        "speed": 0,
        "successRate": 100,
        "tpGain": 0
    },
    {
        "id": 22,
        "animationId": 0,
        "consumable": true,
        "damage": {
            "critical": false,
            "elementId": 0,
            "formula": "0",
            "type": 0,
            "variance": 20
        },
        "description": "使用する事で防御力が1上昇する丸薬。",
        "effects": [
            {
                "code": 42,
                "dataId": 3,
                "value1": 1,
                "value2": 0
            }
        ],
        "hitType": 0,
        "iconIndex": 0,
        "itypeId": 1,
        "name": "成長剤DEF",
        "note": "",
        "occasion": 2,
        "price": 50,
        "repeats": 1,
        "scope": 11,
        "speed": 0,
        "successRate": 100,
        "tpGain": 0
    },
    {
        "id": 23,
        "animationId": 0,
        "consumable": true,
        "damage": {
            "critical": false,
            "elementId": 0,
            "formula": "0",
            "type": 0,
            "variance": 20
        },
        "description": "使用する事で技力が1上昇する丸薬。",
        "effects": [
            {
                "code": 42,
                "dataId": 4,
                "value1": 1,
                "value2": 0
            }
        ],
        "hitType": 0,
        "iconIndex": 0,
        "itypeId": 1,
        "name": "成長剤MAG",
        "note": "",
        "occasion": 2,
        "price": 50,
        "repeats": 1,
        "scope": 11,
        "speed": 0,
        "successRate": 100,
        "tpGain": 0
    },
    {
        "id": 24,
        "animationId": 0,
        "consumable": true,
        "damage": {
            "critical": false,
            "elementId": 0,
            "formula": "0",
            "type": 0,
            "variance": 20
        },
        "description": "使用する事で技耐性が1上昇する丸薬。",
        "effects": [
            {
                "code": 42,
                "dataId": 5,
                "value1": 1,
                "value2": 0
            }
        ],
        "hitType": 0,
        "iconIndex": 0,
        "itypeId": 1,
        "name": "成長剤MDEF",
        "note": "",
        "occasion": 2,
        "price": 50,
        "repeats": 1,
        "scope": 11,
        "speed": 0,
        "successRate": 100,
        "tpGain": 0
    },
    {
        "id": 25,
        "animationId": 0,
        "consumable": true,
        "damage": {
            "critical": false,
            "elementId": 0,
            "formula": "0",
            "type": 0,
            "variance": 20
        },
        "description": "使用する事で敏捷性が1上昇する丸薬。",
        "effects": [
            {
                "code": 42,
                "dataId": 6,
                "value1": 1,
                "value2": 0
            }
        ],
        "hitType": 0,
        "iconIndex": 0,
        "itypeId": 1,
        "name": "成長剤SPD",
        "note": "",
        "occasion": 2,
        "price": 50,
        "repeats": 1,
        "scope": 11,
        "speed": 0,
        "successRate": 100,
        "tpGain": 0
    },
    {
        "id": 26,
        "animationId": 0,
        "consumable": true,
        "damage": {
            "critical": false,
            "elementId": 0,
            "formula": "0",
            "type": 0,
            "variance": 20
        },
        "description": "使用する事で運が1上昇する丸薬。",
        "effects": [
            {
                "code": 42,
                "dataId": 7,
                "value1": 1,
                "value2": 0
            }
        ],
        "hitType": 0,
        "iconIndex": 0,
        "itypeId": 1,
        "name": "成長剤LAK",
        "note": "",
        "occasion": 2,
        "price": 50,
        "repeats": 1,
        "scope": 11,
        "speed": 0,
        "successRate": 100,
        "tpGain": 0
    },
    {
        "id": 27,
        "animationId": 0,
        "consumable": true,
        "damage": {
            "critical": false,
            "elementId": 0,
            "formula": "0",
            "type": 0,
            "variance": 20
        },
        "description": "",
        "effects": [],
        "hitType": 0,
        "iconIndex": 0,
        "itypeId": 1,
        "name": "",
        "note": "",
        "occasion": 0,
        "price": 0,
        "repeats": 1,
        "scope": 7,
        "speed": 0,
        "successRate": 100,
        "tpGain": 0
    },
    {
        "id": 28,
        "animationId": 0,
        "consumable": true,
        "damage": {
            "critical": false,
            "elementId": 0,
            "formula": "0",
            "type": 0,
            "variance": 20
        },
        "description": "換金アイテム。",
        "effects": [],
        "hitType": 0,
        "iconIndex": 0,
        "itypeId": 1,
        "name": "ルーイングラスの粉末",
        "note": "",
        "occasion": 3,
        "price": 10,
        "repeats": 1,
        "scope": 0,
        "speed": 0,
        "successRate": 100,
        "tpGain": 0
    },
    {
        "id": 29,
        "animationId": 0,
        "consumable": true,
        "damage": {
            "critical": false,
            "elementId": 0,
            "formula": "0",
            "type": 0,
            "variance": 20
        },
        "description": "換金アイテム。",
        "effects": [],
        "hitType": 0,
        "iconIndex": 0,
        "itypeId": 1,
        "name": "ルーイングラスの欠片（小）",
        "note": "",
        "occasion": 3,
        "price": 20,
        "repeats": 1,
        "scope": 0,
        "speed": 0,
        "successRate": 100,
        "tpGain": 0
    },
    {
        "id": 30,
        "animationId": 0,
        "consumable": true,
        "damage": {
            "critical": false,
            "elementId": 0,
            "formula": "0",
            "type": 0,
            "variance": 20
        },
        "description": "換金アイテム。",
        "effects": [],
        "hitType": 0,
        "iconIndex": 0,
        "itypeId": 1,
        "name": "ルーイングラスの欠片（大）",
        "note": "",
        "occasion": 3,
        "price": 30,
        "repeats": 1,
        "scope": 0,
        "speed": 0,
        "successRate": 100,
        "tpGain": 0
    },
    {
        "id": 31,
        "animationId": 0,
        "consumable": true,
        "damage": {
            "critical": false,
            "elementId": 0,
            "formula": "0",
            "type": 0,
            "variance": 20
        },
        "description": "換金アイテム。",
        "effects": [],
        "hitType": 0,
        "iconIndex": 0,
        "itypeId": 1,
        "name": "ルーイングラスの結晶",
        "note": "",
        "occasion": 3,
        "price": 50,
        "repeats": 1,
        "scope": 0,
        "speed": 0,
        "successRate": 100,
        "tpGain": 0
    },
    {
        "id": 32,
        "animationId": 0,
        "consumable": true,
        "damage": {
            "critical": false,
            "elementId": 0,
            "formula": "0",
            "type": 0,
            "variance": 20
        },
        "description": "換金アイテム。",
        "effects": [],
        "hitType": 0,
        "iconIndex": 0,
        "itypeId": 1,
        "name": "ルーイングラスの核",
        "note": "",
        "occasion": 3,
        "price": 100,
        "repeats": 1,
        "scope": 0,
        "speed": 0,
        "successRate": 100,
        "tpGain": 0
    },
    {
        "id": 33,
        "animationId": 0,
        "consumable": true,
        "damage": {
            "critical": false,
            "elementId": 0,
            "formula": "0",
            "type": 0,
            "variance": 20
        },
        "description": "使用する事で『応急手当』の使用が可能になる。\n【効果】自身のHPを少量回復する。",
        "effects": [
            {
                "code": 44,
                "dataId": 152,
                "value1": 1,
                "value2": 0
            }
        ],
        "hitType": 0,
        "iconIndex": 0,
        "itypeId": 2,
        "name": "【技法書】応急手当",
        "note": "itemMaxNum:1\n<MNKR_SwitchSell>",
        "occasion": 2,
        "price": 300,
        "repeats": 1,
        "scope": 0,
        "speed": 0,
        "successRate": 100,
        "tpGain": 0
    },
    {
        "id": 34,
        "animationId": 0,
        "consumable": true,
        "damage": {
            "critical": false,
            "elementId": 0,
            "formula": "0",
            "type": 0,
            "variance": 20
        },
        "description": "湖底遺跡内に点在する扉開錠用の鍵。",
        "effects": [],
        "hitType": 0,
        "iconIndex": 0,
        "itypeId": 1,
        "name": "湖底遺跡の鍵",
        "note": "",
        "occasion": 3,
        "price": 150,
        "repeats": 1,
        "scope": 0,
        "speed": 0,
        "successRate": 100,
        "tpGain": 0
    },
    {
        "id": 35,
        "animationId": 0,
        "consumable": true,
        "damage": {
            "critical": false,
            "elementId": 0,
            "formula": "0",
            "type": 0,
            "variance": 20
        },
        "description": "使用する事で『防護の構え』の使用が可能になる。\n【効果】短時間の間、防御力が上昇する。",
        "effects": [
            {
                "code": 44,
                "dataId": 157,
                "value1": 1,
                "value2": 0
            }
        ],
        "hitType": 0,
        "iconIndex": 0,
        "itypeId": 2,
        "name": "【技法書】防護の構え",
        "note": "itemMaxNum:1\n<MNKR_SwitchSell>",
        "occasion": 2,
        "price": 500,
        "repeats": 1,
        "scope": 0,
        "speed": 0,
        "successRate": 100,
        "tpGain": 0
    },
    {
        "id": 36,
        "animationId": 0,
        "consumable": true,
        "damage": {
            "critical": false,
            "elementId": 0,
            "formula": "0",
            "type": 0,
            "variance": 20
        },
        "description": "使用する事で『敏捷の歩法』の使用が可能になる。\n【効果】短時間の間、敏捷性が上昇する。",
        "effects": [
            {
                "code": 44,
                "dataId": 159,
                "value1": 1,
                "value2": 0
            }
        ],
        "hitType": 0,
        "iconIndex": 0,
        "itypeId": 2,
        "name": "【技法書】敏捷の歩法",
        "note": "itemMaxNum:1\n<MNKR_SwitchSell>",
        "occasion": 2,
        "price": 500,
        "repeats": 1,
        "scope": 0,
        "speed": 0,
        "successRate": 100,
        "tpGain": 0
    },
    {
        "id": 37,
        "animationId": 0,
        "consumable": true,
        "damage": {
            "critical": false,
            "elementId": 0,
            "formula": "0",
            "type": 0,
            "variance": 20
        },
        "description": "使用する事で『大打擲』の使用が可能になる。\n【効果】命中率は下がるが、より強い一撃を放つ。",
        "effects": [
            {
                "code": 44,
                "dataId": 160,
                "value1": 1,
                "value2": 0
            }
        ],
        "hitType": 0,
        "iconIndex": 0,
        "itypeId": 2,
        "name": "【技法書】大打擲",
        "note": "itemMaxNum:1\n<MNKR_SwitchSell>",
        "occasion": 2,
        "price": 500,
        "repeats": 1,
        "scope": 0,
        "speed": 0,
        "successRate": 100,
        "tpGain": 0
    },
    {
        "id": 38,
        "animationId": 0,
        "consumable": true,
        "damage": {
            "critical": false,
            "elementId": 0,
            "formula": "0",
            "type": 0,
            "variance": 20
        },
        "description": "使用する事で『穿刃』の使用が可能になる。\n【効果】体力を犠牲にし、敵に防御力無視の攻撃を行なう。",
        "effects": [
            {
                "code": 44,
                "dataId": 149,
                "value1": 1,
                "value2": 0
            }
        ],
        "hitType": 0,
        "iconIndex": 0,
        "itypeId": 2,
        "name": "【技法書】穿刃",
        "note": "<MNKR_SwitchSell>",
        "occasion": 2,
        "price": 0,
        "repeats": 1,
        "scope": 0,
        "speed": 0,
        "successRate": 100,
        "tpGain": 0
    },
    {
        "id": 39,
        "animationId": 0,
        "consumable": true,
        "damage": {
            "critical": false,
            "elementId": 0,
            "formula": "0",
            "type": 0,
            "variance": 20
        },
        "description": "使用する事で『小型榴弾』の使用が可能になる。\n【効果】敵に小型の榴弾を投げつける。",
        "effects": [
            {
                "code": 44,
                "dataId": 150,
                "value1": 1,
                "value2": 0
            }
        ],
        "hitType": 0,
        "iconIndex": 0,
        "itypeId": 2,
        "name": "【技法書】小型榴弾",
        "note": "<MNKR_SwitchSell>",
        "occasion": 2,
        "price": 0,
        "repeats": 1,
        "scope": 0,
        "speed": 0,
        "successRate": 100,
        "tpGain": 0
    },
    {
        "id": 40,
        "animationId": 0,
        "consumable": true,
        "damage": {
            "critical": false,
            "elementId": 0,
            "formula": "0",
            "type": 0,
            "variance": 20
        },
        "description": "",
        "effects": [
            {
                "code": 44,
                "dataId": 150,
                "value1": 1,
                "value2": 0
            }
        ],
        "hitType": 0,
        "iconIndex": 0,
        "itypeId": 2,
        "name": "【技法書】HP20UP",
        "note": "",
        "occasion": 2,
        "price": 0,
        "repeats": 1,
        "scope": 0,
        "speed": 0,
        "successRate": 100,
        "tpGain": 0
    },
    {
        "id": 41,
        "animationId": 0,
        "consumable": true,
        "damage": {
            "critical": false,
            "elementId": 0,
            "formula": "0",
            "type": 0,
            "variance": 20
        },
        "description": "使用する事で『自棄』の使用が可能になる。\n【効果】戦闘中、全てを諦め敗北の道を選ぶ。",
        "effects": [
            {
                "code": 44,
                "dataId": 147,
                "value1": 1,
                "value2": 0
            }
        ],
        "hitType": 0,
        "iconIndex": 0,
        "itypeId": 2,
        "name": "【技法書】自棄",
        "note": "<MNKR_SwitchSell>",
        "occasion": 2,
        "price": 0,
        "repeats": 1,
        "scope": 0,
        "speed": 0,
        "successRate": 100,
        "tpGain": 0
    },
    {
        "id": 42,
        "animationId": 0,
        "consumable": true,
        "damage": {
            "critical": false,
            "elementId": 0,
            "formula": "0",
            "type": 0,
            "variance": 20
        },
        "description": "使用する事で『卵嚢の粘縄』の使用が可能になる。\n【効果】粘糸の束を投擲する。",
        "effects": [
            {
                "code": 44,
                "dataId": 146,
                "value1": 1,
                "value2": 0
            }
        ],
        "hitType": 0,
        "iconIndex": 0,
        "itypeId": 2,
        "name": "【技法書】卵嚢の粘縄",
        "note": "<MNKR_SwitchSell>",
        "occasion": 2,
        "price": 0,
        "repeats": 1,
        "scope": 0,
        "speed": 0,
        "successRate": 100,
        "tpGain": 0
    },
    {
        "id": 43,
        "animationId": 0,
        "consumable": true,
        "damage": {
            "critical": false,
            "elementId": 0,
            "formula": "0",
            "type": 0,
            "variance": 20
        },
        "description": "使用する事で『閃光玉』の使用が可能になる。\n【効果】遺跡の主から作られた特殊な眼眩まし。",
        "effects": [
            {
                "code": 44,
                "dataId": 145,
                "value1": 1,
                "value2": 0
            }
        ],
        "hitType": 0,
        "iconIndex": 0,
        "itypeId": 2,
        "name": "【技法書】閃光玉",
        "note": "<MNKR_SwitchSell>",
        "occasion": 2,
        "price": 0,
        "repeats": 1,
        "scope": 0,
        "speed": 0,
        "successRate": 100,
        "tpGain": 0
    },
    {
        "id": 44,
        "animationId": 0,
        "consumable": true,
        "damage": {
            "critical": false,
            "elementId": 0,
            "formula": "0",
            "type": 0,
            "variance": 20
        },
        "description": "使用する事で『弱性経皮毒』の使用が可能になる。\n【効果】自然排出可能な弱性の毒。",
        "effects": [
            {
                "code": 44,
                "dataId": 144,
                "value1": 1,
                "value2": 0
            }
        ],
        "hitType": 0,
        "iconIndex": 0,
        "itypeId": 2,
        "name": "【技法書】弱性経皮毒",
        "note": "<MNKR_SwitchSell>",
        "occasion": 2,
        "price": 1000,
        "repeats": 1,
        "scope": 0,
        "speed": 0,
        "successRate": 100,
        "tpGain": 0
    },
    {
        "id": 45,
        "animationId": 0,
        "consumable": true,
        "damage": {
            "critical": false,
            "elementId": 0,
            "formula": "0",
            "type": 0,
            "variance": 20
        },
        "description": "使用する事で『回避歩法』の使用が可能になる。\n【効果】一定時間の間、床ダメージを無効化する。",
        "effects": [
            {
                "code": 44,
                "dataId": 143,
                "value1": 1,
                "value2": 0
            }
        ],
        "hitType": 0,
        "iconIndex": 0,
        "itypeId": 2,
        "name": "【技法書】回避歩法",
        "note": "",
        "occasion": 2,
        "price": 200,
        "repeats": 1,
        "scope": 0,
        "speed": 0,
        "successRate": 100,
        "tpGain": 0
    },
    {
        "id": 46,
        "animationId": 0,
        "consumable": true,
        "damage": {
            "critical": false,
            "elementId": 0,
            "formula": "0",
            "type": 0,
            "variance": 20
        },
        "description": "使用する事で『急襲の構え』の使用が可能になる。\n【効果】短時間の間、攻撃力が上昇する。",
        "effects": [
            {
                "code": 44,
                "dataId": 158,
                "value1": 1,
                "value2": 0
            }
        ],
        "hitType": 0,
        "iconIndex": 0,
        "itypeId": 2,
        "name": "【技法書】急襲の構え",
        "note": "itemMaxNum:1\n<MNKR_SwitchSell>",
        "occasion": 2,
        "price": 500,
        "repeats": 1,
        "scope": 0,
        "speed": 0,
        "successRate": 100,
        "tpGain": 0
    },
    {
        "id": 47,
        "animationId": 0,
        "consumable": true,
        "damage": {
            "critical": false,
            "elementId": 0,
            "formula": "0",
            "type": 0,
            "variance": 20
        },
        "description": "使用する事で『治療』の使用が可能になる。\n【効果】出血状態を治療し、HPを極小回復。",
        "effects": [
            {
                "code": 44,
                "dataId": 156,
                "value1": 1,
                "value2": 0
            }
        ],
        "hitType": 0,
        "iconIndex": 0,
        "itypeId": 2,
        "name": "【技法書】治療",
        "note": "itemMaxNum:1\n<MNKR_SwitchSell>",
        "occasion": 2,
        "price": 300,
        "repeats": 1,
        "scope": 0,
        "speed": 0,
        "successRate": 100,
        "tpGain": 0
    },
    {
        "id": 48,
        "animationId": 0,
        "consumable": true,
        "damage": {
            "critical": false,
            "elementId": 0,
            "formula": "0",
            "type": 0,
            "variance": 20
        },
        "description": "使用する事で『戒心の構え』の使用が可能になる。\n【効果】短時間の間、ほぼ全ての能力が僅かに上昇する。",
        "effects": [
            {
                "code": 44,
                "dataId": 151,
                "value1": 1,
                "value2": 0
            }
        ],
        "hitType": 0,
        "iconIndex": 0,
        "itypeId": 2,
        "name": "【技法書】戒心の構え",
        "note": "itemMaxNum:1\n<MNKR_SwitchSell>",
        "occasion": 2,
        "price": 500,
        "repeats": 1,
        "scope": 0,
        "speed": 0,
        "successRate": 100,
        "tpGain": 0
    },
    {
        "id": 49,
        "animationId": 0,
        "consumable": false,
        "damage": {
            "critical": false,
            "elementId": 0,
            "formula": "0",
            "type": 0,
            "variance": 20
        },
        "description": "自宅の鏡にて閲覧可能。",
        "effects": [],
        "hitType": 0,
        "iconIndex": 0,
        "itypeId": 2,
        "name": "立ち絵：給仕衣装裸",
        "note": "itemMaxNum:1\n<MNKR_SwitchSell>",
        "occasion": 3,
        "price": 500,
        "repeats": 1,
        "scope": 0,
        "speed": 0,
        "successRate": 100,
        "tpGain": 0
    },
    {
        "id": 50,
        "animationId": 0,
        "consumable": false,
        "damage": {
            "critical": false,
            "elementId": 0,
            "formula": "0",
            "type": 0,
            "variance": 20
        },
        "description": "自宅の鏡にて閲覧可能。",
        "effects": [],
        "hitType": 0,
        "iconIndex": 0,
        "itypeId": 2,
        "name": "立ち絵：魔淑女の黒衣裸",
        "note": "itemMaxNum:1\n<MNKR_SwitchSell>",
        "occasion": 3,
        "price": 500,
        "repeats": 1,
        "scope": 0,
        "speed": 0,
        "successRate": 100,
        "tpGain": 0
    },
    {
        "id": 51,
        "animationId": 0,
        "consumable": false,
        "damage": {
            "critical": false,
            "elementId": 0,
            "formula": "0",
            "type": 0,
            "variance": 20
        },
        "description": "自宅の鏡にて閲覧可能。",
        "effects": [],
        "hitType": 0,
        "iconIndex": 0,
        "itypeId": 2,
        "name": "立ち絵：日常全裸背面",
        "note": "itemMaxNum:1\n<MNKR_SwitchSell>",
        "occasion": 3,
        "price": 500,
        "repeats": 1,
        "scope": 0,
        "speed": 0,
        "successRate": 100,
        "tpGain": 0
    },
    {
        "id": 52,
        "animationId": 0,
        "consumable": false,
        "damage": {
            "critical": false,
            "elementId": 0,
            "formula": "0",
            "type": 0,
            "variance": 20
        },
        "description": "自宅の鏡にて閲覧可能。",
        "effects": [],
        "hitType": 0,
        "iconIndex": 0,
        "itypeId": 2,
        "name": "立ち絵：日常全裸",
        "note": "itemMaxNum:1\n<MNKR_SwitchSell>",
        "occasion": 3,
        "price": 500,
        "repeats": 1,
        "scope": 0,
        "speed": 0,
        "successRate": 100,
        "tpGain": 0
    },
    {
        "id": 53,
        "animationId": 0,
        "consumable": false,
        "damage": {
            "critical": false,
            "elementId": 0,
            "formula": "0",
            "type": 0,
            "variance": 20
        },
        "description": "自宅の鏡にて閲覧可能。",
        "effects": [],
        "hitType": 0,
        "iconIndex": 0,
        "itypeId": 2,
        "name": "立ち絵：給仕衣装2",
        "note": "itemMaxNum:1\n<MNKR_SwitchSell>",
        "occasion": 3,
        "price": 500,
        "repeats": 1,
        "scope": 0,
        "speed": 0,
        "successRate": 100,
        "tpGain": 0
    },
    {
        "id": 54,
        "animationId": 0,
        "consumable": false,
        "damage": {
            "critical": false,
            "elementId": 0,
            "formula": "0",
            "type": 0,
            "variance": 20
        },
        "description": "自宅の鏡にて閲覧可能。",
        "effects": [],
        "hitType": 0,
        "iconIndex": 0,
        "itypeId": 2,
        "name": "立ち絵：給仕衣装",
        "note": "itemMaxNum:1\n<MNKR_SwitchSell>",
        "occasion": 3,
        "price": 300,
        "repeats": 1,
        "scope": 0,
        "speed": 0,
        "successRate": 100,
        "tpGain": 0
    },
    {
        "id": 55,
        "animationId": 0,
        "consumable": false,
        "damage": {
            "critical": false,
            "elementId": 0,
            "formula": "0",
            "type": 0,
            "variance": 20
        },
        "description": "自宅の鏡にて閲覧可能。",
        "effects": [],
        "hitType": 0,
        "iconIndex": 0,
        "itypeId": 2,
        "name": "立ち絵：魔淑女の黒衣背面",
        "note": "itemMaxNum:1\n<MNKR_SwitchSell>",
        "occasion": 3,
        "price": 500,
        "repeats": 1,
        "scope": 0,
        "speed": 0,
        "successRate": 100,
        "tpGain": 0
    },
    {
        "id": 56,
        "animationId": 0,
        "consumable": false,
        "damage": {
            "critical": false,
            "elementId": 0,
            "formula": "0",
            "type": 0,
            "variance": 20
        },
        "description": "自宅の鏡にて閲覧可能。",
        "effects": [],
        "hitType": 0,
        "iconIndex": 0,
        "itypeId": 2,
        "name": "立ち絵：魔淑女の黒衣",
        "note": "itemMaxNum:1\n<MNKR_SwitchSell>",
        "occasion": 3,
        "price": 500,
        "repeats": 1,
        "scope": 0,
        "speed": 0,
        "successRate": 100,
        "tpGain": 0
    },
    {
        "id": 57,
        "animationId": 0,
        "consumable": false,
        "damage": {
            "critical": false,
            "elementId": 0,
            "formula": "0",
            "type": 0,
            "variance": 20
        },
        "description": "自宅の鏡にて閲覧可能。",
        "effects": [],
        "hitType": 0,
        "iconIndex": 0,
        "itypeId": 2,
        "name": "立ち絵：日常着半裸",
        "note": "itemMaxNum:1\n<MNKR_SwitchSell>",
        "occasion": 3,
        "price": 500,
        "repeats": 1,
        "scope": 0,
        "speed": 0,
        "successRate": 100,
        "tpGain": 0
    },
    {
        "id": 58,
        "animationId": 0,
        "consumable": false,
        "damage": {
            "critical": false,
            "elementId": 0,
            "formula": "0",
            "type": 0,
            "variance": 20
        },
        "description": "自宅の鏡にて閲覧可能。",
        "effects": [],
        "hitType": 0,
        "iconIndex": 0,
        "itypeId": 2,
        "name": "立ち絵：日常着下着背面",
        "note": "itemMaxNum:1\n<MNKR_SwitchSell>",
        "occasion": 3,
        "price": 500,
        "repeats": 1,
        "scope": 0,
        "speed": 0,
        "successRate": 100,
        "tpGain": 0
    },
    {
        "id": 59,
        "animationId": 0,
        "consumable": false,
        "damage": {
            "critical": false,
            "elementId": 0,
            "formula": "0",
            "type": 0,
            "variance": 20
        },
        "description": "自宅の鏡にて閲覧可能。",
        "effects": [],
        "hitType": 0,
        "iconIndex": 0,
        "itypeId": 2,
        "name": "立ち絵：日常着背面",
        "note": "itemMaxNum:1\n<MNKR_SwitchSell>",
        "occasion": 3,
        "price": 500,
        "repeats": 1,
        "scope": 0,
        "speed": 0,
        "successRate": 100,
        "tpGain": 0
    },
    {
        "id": 60,
        "animationId": 0,
        "consumable": false,
        "damage": {
            "critical": false,
            "elementId": 0,
            "formula": "0",
            "type": 0,
            "variance": 20
        },
        "description": "自宅の鏡にて閲覧可能。",
        "effects": [],
        "hitType": 0,
        "iconIndex": 0,
        "itypeId": 2,
        "name": "立ち絵：日常着",
        "note": "itemMaxNum:1\n<MNKR_SwitchSell>",
        "occasion": 3,
        "price": 300,
        "repeats": 1,
        "scope": 0,
        "speed": 0,
        "successRate": 100,
        "tpGain": 0
    },
    {
        "id": 61,
        "animationId": 0,
        "consumable": true,
        "damage": {
            "critical": false,
            "elementId": 0,
            "formula": "0",
            "type": 0,
            "variance": 20
        },
        "description": "マインド・リュダの催淫を軽減する為の錠剤。",
        "effects": [
            {
                "code": 44,
                "dataId": 111,
                "value1": 1,
                "value2": 0
            }
        ],
        "hitType": 0,
        "iconIndex": 0,
        "itypeId": 1,
        "name": "特殊抗鬱剤",
        "note": "",
        "occasion": 0,
        "price": 500,
        "repeats": 1,
        "scope": 11,
        "speed": 0,
        "successRate": 100,
        "tpGain": 0
    },
    {
        "id": 62,
        "animationId": 0,
        "consumable": true,
        "damage": {
            "critical": false,
            "elementId": 0,
            "formula": "0",
            "type": 0,
            "variance": 20
        },
        "description": "使用する事で『必殺』の使用が可能になる。\n【効果】敵に死から逃れられない必殺の一撃を放つ。",
        "effects": [
            {
                "code": 44,
                "dataId": 153,
                "value1": 1,
                "value2": 0
            }
        ],
        "hitType": 0,
        "iconIndex": 0,
        "itypeId": 2,
        "name": "【技法書】必殺",
        "note": "itemMaxNum:1\n<MNKR_SwitchSell>",
        "occasion": 2,
        "price": 500,
        "repeats": 1,
        "scope": 0,
        "speed": 0,
        "successRate": 100,
        "tpGain": 0
    },
    {
        "id": 63,
        "animationId": 0,
        "consumable": true,
        "damage": {
            "critical": false,
            "elementId": 0,
            "formula": "0",
            "type": 0,
            "variance": 20
        },
        "description": "重度の憂鬱を解消する為の錠剤。",
        "effects": [
            {
                "code": 22,
                "dataId": 13,
                "value1": 1,
                "value2": 0
            }
        ],
        "hitType": 0,
        "iconIndex": 0,
        "itypeId": 1,
        "name": "重度抗鬱剤",
        "note": "",
        "occasion": 0,
        "price": 200,
        "repeats": 1,
        "scope": 7,
        "speed": 0,
        "successRate": 100,
        "tpGain": 0
    },
    {
        "id": 64,
        "animationId": 0,
        "consumable": true,
        "damage": {
            "critical": false,
            "elementId": 0,
            "formula": "0",
            "type": 0,
            "variance": 20
        },
        "description": "陰鬱を解消する為の錠剤。",
        "effects": [
            {
                "code": 22,
                "dataId": 13,
                "value1": 1,
                "value2": 0
            }
        ],
        "hitType": 0,
        "iconIndex": 0,
        "itypeId": 1,
        "name": "抗鬱剤",
        "note": "",
        "occasion": 0,
        "price": 50,
        "repeats": 1,
        "scope": 7,
        "speed": 0,
        "successRate": 100,
        "tpGain": 0
    },
    {
        "id": 65,
        "animationId": 0,
        "consumable": true,
        "damage": {
            "critical": false,
            "elementId": 0,
            "formula": "0",
            "type": 0,
            "variance": 20
        },
        "description": "",
        "effects": [],
        "hitType": 0,
        "iconIndex": 0,
        "itypeId": 1,
        "name": "",
        "note": "",
        "occasion": 0,
        "price": 0,
        "repeats": 1,
        "scope": 7,
        "speed": 0,
        "successRate": 100,
        "tpGain": 0
    },
    {
        "id": 66,
        "animationId": 0,
        "consumable": false,
        "damage": {
            "critical": false,
            "elementId": 0,
            "formula": "0",
            "type": 0,
            "variance": 20
        },
        "description": "ユイアの一時免罪用の証書。",
        "effects": [],
        "hitType": 0,
        "iconIndex": 0,
        "itypeId": 2,
        "name": "ユイアの免罪符5",
        "note": "",
        "occasion": 3,
        "price": 0,
        "repeats": 1,
        "scope": 0,
        "speed": 0,
        "successRate": 100,
        "tpGain": 0
    },
    {
        "id": 67,
        "animationId": 0,
        "consumable": false,
        "damage": {
            "critical": false,
            "elementId": 0,
            "formula": "0",
            "type": 0,
            "variance": 20
        },
        "description": "ユイアの一時免罪用の証書。",
        "effects": [],
        "hitType": 0,
        "iconIndex": 0,
        "itypeId": 2,
        "name": "ユイアの免罪符4",
        "note": "",
        "occasion": 3,
        "price": 0,
        "repeats": 1,
        "scope": 0,
        "speed": 0,
        "successRate": 100,
        "tpGain": 0
    },
    {
        "id": 68,
        "animationId": 0,
        "consumable": false,
        "damage": {
            "critical": false,
            "elementId": 0,
            "formula": "0",
            "type": 0,
            "variance": 20
        },
        "description": "ユイアの一時免罪用の証書。",
        "effects": [],
        "hitType": 0,
        "iconIndex": 0,
        "itypeId": 2,
        "name": "ユイアの免罪符3",
        "note": "",
        "occasion": 3,
        "price": 0,
        "repeats": 1,
        "scope": 0,
        "speed": 0,
        "successRate": 100,
        "tpGain": 0
    },
    {
        "id": 69,
        "animationId": 0,
        "consumable": false,
        "damage": {
            "critical": false,
            "elementId": 0,
            "formula": "0",
            "type": 0,
            "variance": 20
        },
        "description": "ユイアの一時免罪用の証書。",
        "effects": [],
        "hitType": 0,
        "iconIndex": 0,
        "itypeId": 2,
        "name": "ユイアの免罪符2",
        "note": "",
        "occasion": 3,
        "price": 0,
        "repeats": 1,
        "scope": 0,
        "speed": 0,
        "successRate": 100,
        "tpGain": 0
    },
    {
        "id": 70,
        "animationId": 0,
        "consumable": false,
        "damage": {
            "critical": false,
            "elementId": 0,
            "formula": "0",
            "type": 0,
            "variance": 20
        },
        "description": "ユイアの一時免罪用の証書。",
        "effects": [],
        "hitType": 0,
        "iconIndex": 0,
        "itypeId": 2,
        "name": "ユイアの免罪符1",
        "note": "",
        "occasion": 3,
        "price": 0,
        "repeats": 1,
        "scope": 0,
        "speed": 0,
        "successRate": 100,
        "tpGain": 0
    },
    {
        "id": 71,
        "animationId": 0,
        "consumable": false,
        "damage": {
            "critical": false,
            "elementId": 0,
            "formula": "0",
            "type": 0,
            "variance": 20
        },
        "description": "リュダの背信者ツェダの身に着けていた徽章。\n管理所内の書庫に提出する事で『行軍記録』が閲覧出来る。",
        "effects": [],
        "hitType": 0,
        "iconIndex": 0,
        "itypeId": 2,
        "name": "ツェダの徽章",
        "note": "",
        "occasion": 3,
        "price": 0,
        "repeats": 1,
        "scope": 0,
        "speed": 0,
        "successRate": 100,
        "tpGain": 0
    },
    {
        "id": 72,
        "animationId": 0,
        "consumable": false,
        "damage": {
            "critical": false,
            "elementId": 0,
            "formula": "0",
            "type": 0,
            "variance": 20
        },
        "description": "遺跡で入手した怪物の表皮組織。\n管理所内の書庫に提出する事で『行軍記録』が閲覧出来る。",
        "effects": [],
        "hitType": 0,
        "iconIndex": 0,
        "itypeId": 2,
        "name": "遺跡下層の主の細胞",
        "note": "",
        "occasion": 3,
        "price": 0,
        "repeats": 1,
        "scope": 0,
        "speed": 0,
        "successRate": 100,
        "tpGain": 0
    },
    {
        "id": 73,
        "animationId": 0,
        "consumable": false,
        "damage": {
            "critical": false,
            "elementId": 0,
            "formula": "0",
            "type": 0,
            "variance": 20
        },
        "description": "遺跡で入手した怪物の表皮組織。\n管理所内の書庫に提出する事で『行軍記録』が閲覧出来る。",
        "effects": [],
        "hitType": 0,
        "iconIndex": 0,
        "itypeId": 2,
        "name": "遺跡中層の主の細胞",
        "note": "",
        "occasion": 3,
        "price": 0,
        "repeats": 1,
        "scope": 0,
        "speed": 0,
        "successRate": 100,
        "tpGain": 0
    },
    {
        "id": 74,
        "animationId": 0,
        "consumable": false,
        "damage": {
            "critical": false,
            "elementId": 0,
            "formula": "0",
            "type": 0,
            "variance": 20
        },
        "description": "遺跡で入手した怪物の表皮組織。\n管理所内の書庫に提出する事で『行軍記録』が閲覧出来る。",
        "effects": [],
        "hitType": 0,
        "iconIndex": 0,
        "itypeId": 2,
        "name": "遺跡上層の主の細胞",
        "note": "",
        "occasion": 3,
        "price": 0,
        "repeats": 1,
        "scope": 0,
        "speed": 0,
        "successRate": 100,
        "tpGain": 0
    },
    {
        "id": 75,
        "animationId": 0,
        "consumable": false,
        "damage": {
            "critical": false,
            "elementId": 0,
            "formula": "0",
            "type": 0,
            "variance": 20
        },
        "description": "遺跡で入手した怪物の表皮組織。\n管理所内の書庫に提出する事で『行軍記録』が閲覧出来る。",
        "effects": [],
        "hitType": 0,
        "iconIndex": 0,
        "itypeId": 2,
        "name": "遺跡最上層の主細胞",
        "note": "",
        "occasion": 3,
        "price": 0,
        "repeats": 1,
        "scope": 0,
        "speed": 0,
        "successRate": 100,
        "tpGain": 0
    },
    {
        "id": 76,
        "animationId": 0,
        "consumable": false,
        "damage": {
            "critical": false,
            "elementId": 0,
            "formula": "0",
            "type": 0,
            "variance": 20
        },
        "description": "『リュダ行軍記録 6』\n独立夜警国家「暁の穂」行軍禄閲覧許可証。",
        "effects": [],
        "hitType": 0,
        "iconIndex": 0,
        "itypeId": 2,
        "name": "リュダ行軍記録 閲覧許可証 6",
        "note": "<mat1:I82*1>\n<MNKR_SwitchSell>\nitemMaxNum:1",
        "occasion": 3,
        "price": 300,
        "repeats": 1,
        "scope": 0,
        "speed": 0,
        "successRate": 100,
        "tpGain": 0
    },
    {
        "id": 77,
        "animationId": 0,
        "consumable": false,
        "damage": {
            "critical": false,
            "elementId": 0,
            "formula": "0",
            "type": 0,
            "variance": 20
        },
        "description": "『リュダ行軍記録 5』\n独立夜警国家「暁の穂」行軍禄閲覧許可証。",
        "effects": [],
        "hitType": 0,
        "iconIndex": 0,
        "itypeId": 2,
        "name": "リュダ行軍記録 閲覧許可証 5",
        "note": "<mat1:I71*1>\n<MNKR_SwitchSell>\nitemMaxNum:1",
        "occasion": 3,
        "price": 300,
        "repeats": 1,
        "scope": 0,
        "speed": 0,
        "successRate": 100,
        "tpGain": 0
    },
    {
        "id": 78,
        "animationId": 0,
        "consumable": false,
        "damage": {
            "critical": false,
            "elementId": 0,
            "formula": "0",
            "type": 0,
            "variance": 20
        },
        "description": "『リュダ行軍記録 4』\n独立夜警国家「暁の穂」行軍禄閲覧許可証。",
        "effects": [],
        "hitType": 0,
        "iconIndex": 0,
        "itypeId": 2,
        "name": "リュダ行軍記録 閲覧許可証 4",
        "note": "<mat1:I72*1>\n<MNKR_SwitchSell>\nitemMaxNum:1",
        "occasion": 3,
        "price": 300,
        "repeats": 1,
        "scope": 0,
        "speed": 0,
        "successRate": 100,
        "tpGain": 0
    },
    {
        "id": 79,
        "animationId": 0,
        "consumable": false,
        "damage": {
            "critical": false,
            "elementId": 0,
            "formula": "0",
            "type": 0,
            "variance": 20
        },
        "description": "『リュダ行軍記録 3』\n独立夜警国家「暁の穂」行軍禄閲覧許可証。",
        "effects": [],
        "hitType": 0,
        "iconIndex": 0,
        "itypeId": 2,
        "name": "リュダ行軍記録 閲覧許可証 3",
        "note": "<mat1:I73*1>\n<MNKR_SwitchSell>\nitemMaxNum:1",
        "occasion": 3,
        "price": 300,
        "repeats": 1,
        "scope": 0,
        "speed": 0,
        "successRate": 100,
        "tpGain": 0
    },
    {
        "id": 80,
        "animationId": 0,
        "consumable": false,
        "damage": {
            "critical": false,
            "elementId": 0,
            "formula": "0",
            "type": 0,
            "variance": 20
        },
        "description": "『リュダ行軍記録 2』\n独立夜警国家「暁の穂」行軍禄閲覧許可証。",
        "effects": [],
        "hitType": 0,
        "iconIndex": 0,
        "itypeId": 2,
        "name": "リュダ行軍記録 閲覧許可証 2",
        "note": "<mat1:I74*1>\n<MNKR_SwitchSell>\nitemMaxNum:1",
        "occasion": 3,
        "price": 300,
        "repeats": 1,
        "scope": 0,
        "speed": 0,
        "successRate": 100,
        "tpGain": 0
    },
    {
        "id": 81,
        "animationId": 0,
        "consumable": false,
        "damage": {
            "critical": false,
            "elementId": 0,
            "formula": "0",
            "type": 0,
            "variance": 20
        },
        "description": "『リュダ行軍記録 1』\n独立夜警国家「暁の穂」行軍禄閲覧許可証。",
        "effects": [],
        "hitType": 0,
        "iconIndex": 0,
        "itypeId": 2,
        "name": "リュダ行軍記録 閲覧許可証 1",
        "note": "<mat1:I75*1>\n<MNKR_SwitchSell>\nitemMaxNum:1",
        "occasion": 3,
        "price": 300,
        "repeats": 1,
        "scope": 0,
        "speed": 0,
        "successRate": 100,
        "tpGain": 0
    },
    {
        "id": 82,
        "animationId": 0,
        "consumable": false,
        "damage": {
            "critical": false,
            "elementId": 0,
            "formula": "0",
            "type": 0,
            "variance": 20
        },
        "description": "練兵会終了に伴い配布された証書。\n管理所内の書庫に提出する事で『行軍記録』が閲覧出来る。",
        "effects": [],
        "hitType": 0,
        "iconIndex": 0,
        "itypeId": 2,
        "name": "練兵会終了証",
        "note": "itemMaxNum:1",
        "occasion": 3,
        "price": 0,
        "repeats": 1,
        "scope": 0,
        "speed": 0,
        "successRate": 100,
        "tpGain": 0
    },
    {
        "id": 83,
        "animationId": 143,
        "consumable": true,
        "damage": {
            "critical": false,
            "elementId": 0,
            "formula": "100 + a.mat * 2 - b.mdf * 2",
            "type": 1,
            "variance": 10
        },
        "description": "イリメから譲り受けた武具。遺跡の主を怯ませるのに有効。",
        "effects": [
            {
                "code": 21,
                "dataId": 34,
                "value1": 1,
                "value2": 0
            }
        ],
        "hitType": 0,
        "iconIndex": 0,
        "itypeId": 1,
        "name": "炸裂弾",
        "note": "",
        "occasion": 1,
        "price": 0,
        "repeats": 1,
        "scope": 1,
        "speed": 0,
        "successRate": 100,
        "tpGain": 0
    },
    {
        "id": 84,
        "animationId": 0,
        "consumable": true,
        "damage": {
            "critical": false,
            "elementId": 0,
            "formula": "0",
            "type": 0,
            "variance": 20
        },
        "description": "",
        "effects": [
            {
                "code": 44,
                "dataId": 1,
                "value1": 1,
                "value2": 0
            }
        ],
        "hitType": 0,
        "iconIndex": 0,
        "itypeId": 1,
        "name": "CG",
        "note": "",
        "occasion": 0,
        "price": 0,
        "repeats": 1,
        "scope": 7,
        "speed": 0,
        "successRate": 100,
        "tpGain": 0
    },
    {
        "id": 85,
        "animationId": 0,
        "consumable": false,
        "damage": {
            "critical": false,
            "elementId": 0,
            "formula": "0",
            "type": 0,
            "variance": 20
        },
        "description": "ラメがリイアの誕生祝いに用意したささやかな贈り物。",
        "effects": [],
        "hitType": 0,
        "iconIndex": 0,
        "itypeId": 2,
        "name": "ラメの贈り物",
        "note": "",
        "occasion": 3,
        "price": 0,
        "repeats": 1,
        "scope": 7,
        "speed": 0,
        "successRate": 100,
        "tpGain": 0
    },
    {
        "id": 86,
        "animationId": 0,
        "consumable": false,
        "damage": {
            "critical": false,
            "elementId": 0,
            "formula": "0",
            "type": 0,
            "variance": 20
        },
        "description": "薬学の書籍に記載されていた毒草。",
        "effects": [],
        "hitType": 0,
        "iconIndex": 0,
        "itypeId": 1,
        "name": "毒草",
        "note": "",
        "occasion": 3,
        "price": 50,
        "repeats": 1,
        "scope": 0,
        "speed": 0,
        "successRate": 100,
        "tpGain": 0
    },
    {
        "id": 87,
        "animationId": 0,
        "consumable": false,
        "damage": {
            "critical": false,
            "elementId": 0,
            "formula": "0",
            "type": 0,
            "variance": 20
        },
        "description": "閲覧する事で薬学の為の知識が得られる。",
        "effects": [
            {
                "code": 44,
                "dataId": 109,
                "value1": 1,
                "value2": 0
            }
        ],
        "hitType": 0,
        "iconIndex": 0,
        "itypeId": 1,
        "name": "薬学の書籍",
        "note": "itemMaxNum:1",
        "occasion": 2,
        "price": 500,
        "repeats": 1,
        "scope": 0,
        "speed": 0,
        "successRate": 100,
        "tpGain": 0
    },
    {
        "id": 88,
        "animationId": 0,
        "consumable": false,
        "damage": {
            "critical": false,
            "elementId": 0,
            "formula": "0",
            "type": 0,
            "variance": 20
        },
        "description": "夜警国家「暁の穂」大公一族に伝わる首飾り。",
        "effects": [],
        "hitType": 0,
        "iconIndex": 0,
        "itypeId": 2,
        "name": "暁の穂の首飾り",
        "note": "",
        "occasion": 3,
        "price": 0,
        "repeats": 1,
        "scope": 0,
        "speed": 0,
        "successRate": 100,
        "tpGain": 0
    },
    {
        "id": 89,
        "animationId": 0,
        "consumable": false,
        "damage": {
            "critical": false,
            "elementId": 0,
            "formula": "0",
            "type": 0,
            "variance": 20
        },
        "description": "死刑囚ゾゾイェを捕縛、連行する際に使用された薬。",
        "effects": [],
        "hitType": 0,
        "iconIndex": 0,
        "itypeId": 2,
        "name": "リュダの阻害薬",
        "note": "",
        "occasion": 3,
        "price": 0,
        "repeats": 1,
        "scope": 0,
        "speed": 0,
        "successRate": 100,
        "tpGain": 0
    },
    {
        "id": 90,
        "animationId": 0,
        "consumable": false,
        "damage": {
            "critical": false,
            "elementId": 0,
            "formula": "0",
            "type": 0,
            "variance": 20
        },
        "description": "遺跡最下層で入手した数滴の液体。",
        "effects": [],
        "hitType": 0,
        "iconIndex": 0,
        "itypeId": 2,
        "name": "遺跡最下層の液体",
        "note": "",
        "occasion": 3,
        "price": 0,
        "repeats": 1,
        "scope": 0,
        "speed": 0,
        "successRate": 100,
        "tpGain": 0
    },
    {
        "id": 91,
        "animationId": 0,
        "consumable": false,
        "damage": {
            "critical": false,
            "elementId": 0,
            "formula": "0",
            "type": 0,
            "variance": 20
        },
        "description": "セギの手帳。色々と書き込める。第5戦用。",
        "effects": [
            {
                "code": 44,
                "dataId": 106,
                "value1": 1,
                "value2": 0
            }
        ],
        "hitType": 0,
        "iconIndex": 0,
        "itypeId": 2,
        "name": "メモ帳",
        "note": "",
        "occasion": 2,
        "price": 0,
        "repeats": 1,
        "scope": 0,
        "speed": 0,
        "successRate": 100,
        "tpGain": 0
    },
    {
        "id": 92,
        "animationId": 0,
        "consumable": false,
        "damage": {
            "critical": false,
            "elementId": 0,
            "formula": "0",
            "type": 0,
            "variance": 20
        },
        "description": "セギの手帳。色々と書き込める。第4戦用。",
        "effects": [
            {
                "code": 44,
                "dataId": 105,
                "value1": 1,
                "value2": 0
            }
        ],
        "hitType": 0,
        "iconIndex": 0,
        "itypeId": 2,
        "name": "メモ帳",
        "note": "",
        "occasion": 2,
        "price": 0,
        "repeats": 1,
        "scope": 0,
        "speed": 0,
        "successRate": 100,
        "tpGain": 0
    },
    {
        "id": 93,
        "animationId": 0,
        "consumable": false,
        "damage": {
            "critical": false,
            "elementId": 0,
            "formula": "0",
            "type": 0,
            "variance": 20
        },
        "description": "セギの手帳。色々と書き込める。第3戦用。",
        "effects": [
            {
                "code": 44,
                "dataId": 104,
                "value1": 1,
                "value2": 0
            }
        ],
        "hitType": 0,
        "iconIndex": 0,
        "itypeId": 2,
        "name": "メモ帳",
        "note": "",
        "occasion": 2,
        "price": 0,
        "repeats": 1,
        "scope": 0,
        "speed": 0,
        "successRate": 100,
        "tpGain": 0
    },
    {
        "id": 94,
        "animationId": 0,
        "consumable": false,
        "damage": {
            "critical": false,
            "elementId": 0,
            "formula": "0",
            "type": 0,
            "variance": 20
        },
        "description": "セギの手帳。色々と書き込める。第2戦用。",
        "effects": [
            {
                "code": 44,
                "dataId": 103,
                "value1": 1,
                "value2": 0
            }
        ],
        "hitType": 0,
        "iconIndex": 0,
        "itypeId": 2,
        "name": "メモ帳",
        "note": "",
        "occasion": 2,
        "price": 0,
        "repeats": 1,
        "scope": 0,
        "speed": 0,
        "successRate": 100,
        "tpGain": 0
    },
    {
        "id": 95,
        "animationId": 0,
        "consumable": false,
        "damage": {
            "critical": false,
            "elementId": 0,
            "formula": "0",
            "type": 0,
            "variance": 20
        },
        "description": "セギの手帳。色々と書き込める。初戦用。",
        "effects": [
            {
                "code": 44,
                "dataId": 102,
                "value1": 1,
                "value2": 0
            }
        ],
        "hitType": 0,
        "iconIndex": 0,
        "itypeId": 2,
        "name": "メモ帳",
        "note": "",
        "occasion": 2,
        "price": 0,
        "repeats": 1,
        "scope": 0,
        "speed": 0,
        "successRate": 100,
        "tpGain": 0
    },
    {
        "id": 96,
        "animationId": 0,
        "consumable": false,
        "damage": {
            "critical": false,
            "elementId": 0,
            "formula": "0",
            "type": 0,
            "variance": 20
        },
        "description": "酒場の店主から依頼された原料。",
        "effects": [],
        "hitType": 0,
        "iconIndex": 0,
        "itypeId": 1,
        "name": "アルコール材料",
        "note": "",
        "occasion": 3,
        "price": 0,
        "repeats": 1,
        "scope": 7,
        "speed": 0,
        "successRate": 100,
        "tpGain": 0
    },
    {
        "id": 97,
        "animationId": 0,
        "consumable": false,
        "damage": {
            "critical": false,
            "elementId": 0,
            "formula": "0",
            "type": 0,
            "variance": 20
        },
        "description": "",
        "effects": [],
        "hitType": 0,
        "iconIndex": 0,
        "itypeId": 2,
        "name": "遺跡の主の卵嚢",
        "note": "",
        "occasion": 3,
        "price": 0,
        "repeats": 1,
        "scope": 0,
        "speed": 0,
        "successRate": 100,
        "tpGain": 0
    },
    {
        "id": 98,
        "animationId": 0,
        "consumable": true,
        "damage": {
            "critical": false,
            "elementId": 0,
            "formula": "0",
            "type": 0,
            "variance": 20
        },
        "description": "",
        "effects": [
            {
                "code": 44,
                "dataId": 44,
                "value1": 1,
                "value2": 0
            }
        ],
        "hitType": 0,
        "iconIndex": 0,
        "itypeId": 1,
        "name": "スキル本HP20UP",
        "note": "",
        "occasion": 2,
        "price": 0,
        "repeats": 1,
        "scope": 7,
        "speed": 0,
        "successRate": 100,
        "tpGain": 0
    },
    {
        "id": 99,
        "animationId": 0,
        "consumable": false,
        "damage": {
            "critical": false,
            "elementId": 0,
            "formula": "0",
            "type": 0,
            "variance": 20
        },
        "description": "遺跡で入手した怪物の表皮組織。",
        "effects": [],
        "hitType": 0,
        "iconIndex": 0,
        "itypeId": 2,
        "name": "輝く鱗",
        "note": "",
        "occasion": 3,
        "price": 0,
        "repeats": 1,
        "scope": 0,
        "speed": 0,
        "successRate": 100,
        "tpGain": 0
    },
    {
        "id": 100,
        "animationId": 0,
        "consumable": true,
        "damage": {
            "critical": false,
            "elementId": 0,
            "formula": "0",
            "type": 0,
            "variance": 20
        },
        "description": "城内に於ける大公夫婦私室の鍵。",
        "effects": [],
        "hitType": 0,
        "iconIndex": 0,
        "itypeId": 2,
        "name": "大公夫婦私室のカギ",
        "note": "",
        "occasion": 3,
        "price": 0,
        "repeats": 1,
        "scope": 7,
        "speed": 0,
        "successRate": 100,
        "tpGain": 0
    },
    {
        "id": 101,
        "animationId": 0,
        "consumable": true,
        "damage": {
            "critical": false,
            "elementId": 0,
            "formula": "0",
            "type": 0,
            "variance": 20
        },
        "description": "湖底遺跡内に存在する扉開錠用の特注品の鍵。",
        "effects": [],
        "hitType": 0,
        "iconIndex": 0,
        "itypeId": 2,
        "name": "湖底遺跡の鍵(特注）",
        "note": "itemMaxNum:1\n<MNKR_SwitchSell>",
        "occasion": 3,
        "price": 300,
        "repeats": 1,
        "scope": 0,
        "speed": 0,
        "successRate": 100,
        "tpGain": 0
    },
    {
        "id": 102,
        "animationId": 0,
        "consumable": true,
        "damage": {
            "critical": false,
            "elementId": 0,
            "formula": "0",
            "type": 0,
            "variance": 20
        },
        "description": "",
        "effects": [],
        "hitType": 0,
        "iconIndex": 0,
        "itypeId": 1,
        "name": "",
        "note": "",
        "occasion": 0,
        "price": 0,
        "repeats": 1,
        "scope": 7,
        "speed": 0,
        "successRate": 100,
        "tpGain": 0
    },
    {
        "id": 103,
        "animationId": 0,
        "consumable": true,
        "damage": {
            "critical": false,
            "elementId": 0,
            "formula": "0",
            "type": 0,
            "variance": 20
        },
        "description": "",
        "effects": [],
        "hitType": 0,
        "iconIndex": 0,
        "itypeId": 1,
        "name": "",
        "note": "",
        "occasion": 0,
        "price": 0,
        "repeats": 1,
        "scope": 7,
        "speed": 0,
        "successRate": 100,
        "tpGain": 0
    },
    {
        "id": 104,
        "animationId": 0,
        "consumable": true,
        "damage": {
            "critical": false,
            "elementId": 0,
            "formula": "0",
            "type": 0,
            "variance": 20
        },
        "description": "",
        "effects": [],
        "hitType": 0,
        "iconIndex": 0,
        "itypeId": 1,
        "name": "",
        "note": "",
        "occasion": 0,
        "price": 0,
        "repeats": 1,
        "scope": 7,
        "speed": 0,
        "successRate": 100,
        "tpGain": 0
    },
    {
        "id": 105,
        "animationId": 0,
        "consumable": true,
        "damage": {
            "critical": false,
            "elementId": 0,
            "formula": "0",
            "type": 0,
            "variance": 20
        },
        "description": "",
        "effects": [],
        "hitType": 0,
        "iconIndex": 0,
        "itypeId": 1,
        "name": "",
        "note": "",
        "occasion": 0,
        "price": 0,
        "repeats": 1,
        "scope": 7,
        "speed": 0,
        "successRate": 100,
        "tpGain": 0
    },
    {
        "id": 106,
        "animationId": 0,
        "consumable": true,
        "damage": {
            "critical": false,
            "elementId": 0,
            "formula": "0",
            "type": 0,
            "variance": 20
        },
        "description": "",
        "effects": [],
        "hitType": 0,
        "iconIndex": 0,
        "itypeId": 1,
        "name": "",
        "note": "",
        "occasion": 0,
        "price": 0,
        "repeats": 1,
        "scope": 7,
        "speed": 0,
        "successRate": 100,
        "tpGain": 0
    },
    {
        "id": 107,
        "animationId": 0,
        "consumable": true,
        "damage": {
            "critical": false,
            "elementId": 0,
            "formula": "0",
            "type": 0,
            "variance": 20
        },
        "description": "",
        "effects": [],
        "hitType": 0,
        "iconIndex": 0,
        "itypeId": 1,
        "name": "",
        "note": "",
        "occasion": 0,
        "price": 0,
        "repeats": 1,
        "scope": 7,
        "speed": 0,
        "successRate": 100,
        "tpGain": 0
    },
    {
        "id": 108,
        "animationId": 0,
        "consumable": true,
        "damage": {
            "critical": false,
            "elementId": 0,
            "formula": "0",
            "type": 0,
            "variance": 20
        },
        "description": "",
        "effects": [],
        "hitType": 0,
        "iconIndex": 0,
        "itypeId": 1,
        "name": "",
        "note": "",
        "occasion": 0,
        "price": 0,
        "repeats": 1,
        "scope": 7,
        "speed": 0,
        "successRate": 100,
        "tpGain": 0
    },
    {
        "id": 109,
        "animationId": 0,
        "consumable": true,
        "damage": {
            "critical": false,
            "elementId": 0,
            "formula": "0",
            "type": 0,
            "variance": 20
        },
        "description": "",
        "effects": [],
        "hitType": 0,
        "iconIndex": 0,
        "itypeId": 1,
        "name": "",
        "note": "",
        "occasion": 0,
        "price": 0,
        "repeats": 1,
        "scope": 7,
        "speed": 0,
        "successRate": 100,
        "tpGain": 0
    },
    {
        "id": 110,
        "animationId": 0,
        "consumable": true,
        "damage": {
            "critical": false,
            "elementId": 0,
            "formula": "0",
            "type": 0,
            "variance": 20
        },
        "description": "",
        "effects": [],
        "hitType": 0,
        "iconIndex": 0,
        "itypeId": 1,
        "name": "",
        "note": "",
        "occasion": 0,
        "price": 0,
        "repeats": 1,
        "scope": 7,
        "speed": 0,
        "successRate": 100,
        "tpGain": 0
    },
    {
        "id": 111,
        "animationId": 0,
        "consumable": true,
        "damage": {
            "critical": false,
            "elementId": 0,
            "formula": "0",
            "type": 0,
            "variance": 20
        },
        "description": "",
        "effects": [],
        "hitType": 0,
        "iconIndex": 0,
        "itypeId": 1,
        "name": "",
        "note": "",
        "occasion": 0,
        "price": 0,
        "repeats": 1,
        "scope": 7,
        "speed": 0,
        "successRate": 100,
        "tpGain": 0
    },
    {
        "id": 112,
        "animationId": 0,
        "consumable": true,
        "damage": {
            "critical": false,
            "elementId": 0,
            "formula": "0",
            "type": 0,
            "variance": 20
        },
        "description": "",
        "effects": [],
        "hitType": 0,
        "iconIndex": 0,
        "itypeId": 1,
        "name": "",
        "note": "",
        "occasion": 0,
        "price": 0,
        "repeats": 1,
        "scope": 7,
        "speed": 0,
        "successRate": 100,
        "tpGain": 0
    },
    {
        "id": 113,
        "animationId": 0,
        "consumable": true,
        "damage": {
            "critical": false,
            "elementId": 0,
            "formula": "0",
            "type": 0,
            "variance": 20
        },
        "description": "",
        "effects": [],
        "hitType": 0,
        "iconIndex": 0,
        "itypeId": 1,
        "name": "",
        "note": "",
        "occasion": 0,
        "price": 0,
        "repeats": 1,
        "scope": 7,
        "speed": 0,
        "successRate": 100,
        "tpGain": 0
    },
    {
        "id": 114,
        "animationId": 0,
        "consumable": true,
        "damage": {
            "critical": false,
            "elementId": 0,
            "formula": "0",
            "type": 0,
            "variance": 20
        },
        "description": "",
        "effects": [],
        "hitType": 0,
        "iconIndex": 0,
        "itypeId": 1,
        "name": "",
        "note": "",
        "occasion": 0,
        "price": 0,
        "repeats": 1,
        "scope": 7,
        "speed": 0,
        "successRate": 100,
        "tpGain": 0
    },
    {
        "id": 115,
        "animationId": 0,
        "consumable": true,
        "damage": {
            "critical": false,
            "elementId": 0,
            "formula": "0",
            "type": 0,
            "variance": 20
        },
        "description": "",
        "effects": [],
        "hitType": 0,
        "iconIndex": 0,
        "itypeId": 1,
        "name": "",
        "note": "",
        "occasion": 0,
        "price": 0,
        "repeats": 1,
        "scope": 7,
        "speed": 0,
        "successRate": 100,
        "tpGain": 0
    },
    {
        "id": 116,
        "animationId": 0,
        "consumable": false,
        "damage": {
            "critical": false,
            "elementId": 0,
            "formula": "0",
            "type": 0,
            "variance": 20
        },
        "description": "セギの私物。売却用。",
        "effects": [],
        "hitType": 0,
        "iconIndex": 0,
        "itypeId": 2,
        "name": "セギの下着3",
        "note": "",
        "occasion": 3,
        "price": 0,
        "repeats": 1,
        "scope": 0,
        "speed": 0,
        "successRate": 100,
        "tpGain": 0
    },
    {
        "id": 117,
        "animationId": 0,
        "consumable": false,
        "damage": {
            "critical": false,
            "elementId": 0,
            "formula": "0",
            "type": 0,
            "variance": 20
        },
        "description": "セギの私物。売却用。",
        "effects": [],
        "hitType": 0,
        "iconIndex": 0,
        "itypeId": 2,
        "name": "セギの下着2",
        "note": "",
        "occasion": 3,
        "price": 0,
        "repeats": 1,
        "scope": 0,
        "speed": 0,
        "successRate": 100,
        "tpGain": 0
    },
    {
        "id": 118,
        "animationId": 0,
        "consumable": false,
        "damage": {
            "critical": false,
            "elementId": 0,
            "formula": "0",
            "type": 0,
            "variance": 20
        },
        "description": "セギの私物。売却用。",
        "effects": [],
        "hitType": 0,
        "iconIndex": 0,
        "itypeId": 2,
        "name": "セギの下着1",
        "note": "",
        "occasion": 3,
        "price": 0,
        "repeats": 1,
        "scope": 0,
        "speed": 0,
        "successRate": 100,
        "tpGain": 0
    },
    {
        "id": 119,
        "animationId": 0,
        "consumable": false,
        "damage": {
            "critical": false,
            "elementId": 0,
            "formula": "0",
            "type": 0,
            "variance": 20
        },
        "description": "セギの私物。売却用。",
        "effects": [],
        "hitType": 0,
        "iconIndex": 0,
        "itypeId": 2,
        "name": "セギの日常着2",
        "note": "",
        "occasion": 3,
        "price": 0,
        "repeats": 1,
        "scope": 0,
        "speed": 0,
        "successRate": 100,
        "tpGain": 0
    },
    {
        "id": 120,
        "animationId": 0,
        "consumable": false,
        "damage": {
            "critical": false,
            "elementId": 0,
            "formula": "0",
            "type": 0,
            "variance": 20
        },
        "description": "セギの私物。売却用。",
        "effects": [],
        "hitType": 0,
        "iconIndex": 0,
        "itypeId": 2,
        "name": "セギの日常着",
        "note": "",
        "occasion": 3,
        "price": 0,
        "repeats": 1,
        "scope": 0,
        "speed": 0,
        "successRate": 100,
        "tpGain": 0
    }
]